CMakeLists.txt
LICENSE.txt
MANIFEST.in
README.md
setup.py
cmake_modules/FindNumPy.cmake
rodentia/__init__.py
rodentia/__version__.py
rodentia/core.py
rodentia.egg-info/PKG-INFO
rodentia.egg-info/SOURCES.txt
rodentia.egg-info/dependency_links.txt
rodentia.egg-info/not-zip-safe
rodentia.egg-info/requires.txt
rodentia.egg-info/top_level.txt
src/CMakeLists.txt
src/common/glinc.h
src/env/Action.h
src/env/CollisionShapeManager.cpp
src/env/CollisionShapeManager.h
src/env/Environment.cpp
src/env/Environment.h
src/env/EnvironmentObject.cpp
src/env/EnvironmentObject.h
src/env/RigidBodyComponent.cpp
src/env/RigidBodyComponent.h
src/geom/BoundingBox.cpp
src/geom/BoundingBox.h
src/geom/Matrix3f.h
src/geom/Matrix4f.h
src/geom/Vector3f.h
src/geom/Vector4f.h
src/importer/ObjImporter.cpp
src/importer/ObjImporter.h
src/importer/tiny_obj_loader.h
src/python/rodentia_module.cpp
src/render/BufferObjects.h
src/render/Camera.cpp
src/render/Camera.h
src/render/CameraView.cpp
src/render/CameraView.h
src/render/CollisionMeshData.h
src/render/DebugDrawer.cpp
src/render/DebugDrawer.h
src/render/DepthFrameBuffer.cpp
src/render/DepthFrameBuffer.h
src/render/DiffuseShader.cpp
src/render/DiffuseShader.h
src/render/DrawComponent.cpp
src/render/DrawComponent.h
src/render/GLContext.cpp
src/render/GLContext.h
src/render/Image.cpp
src/render/Image.h
src/render/LSPSM.cpp
src/render/LSPSM.h
src/render/LineShader.cpp
src/render/LineShader.h
src/render/Material.cpp
src/render/Material.h
src/render/Mesh.cpp
src/render/Mesh.h
src/render/MeshData.cpp
src/render/MeshData.h
src/render/MeshFace.cpp
src/render/MeshFace.h
src/render/MeshFaceData.cpp
src/render/MeshFaceData.h
src/render/MeshManager.cpp
src/render/MeshManager.h
src/render/OffscreenFrameBuffer.cpp
src/render/OffscreenFrameBuffer.h
src/render/PNGDecoder.cpp
src/render/PNGDecoder.h
src/render/RenderTarget.cpp
src/render/RenderTarget.h
src/render/RenderingContext.cpp
src/render/RenderingContext.h
src/render/Shader.cpp
src/render/Shader.h
src/render/ShaderManager.cpp
src/render/ShaderManager.h
src/render/ShadowDepthShader.cpp
src/render/ShadowDepthShader.h
src/render/ShadowDiffuseShader.cpp
src/render/ShadowDiffuseShader.h
