Metadata-Version: 2.1
Name: rodentia
Version: 0.0.9
Summary: 3D reinforcement learning platform
Home-page: https://github.com/miyosuda/rodentia
Author: Kosuke Miyoshi
Author-email: miyosuda@gmail.com
License: Apache 2.0
Keywords: rodentia,ai,deep learning,reinforcement learning,research
Platform: UNKNOWN
Classifier: Development Status :: 3 - Alpha
Classifier: Intended Audience :: Science/Research
Classifier: Topic :: Scientific/Engineering :: Artificial Intelligence
Classifier: License :: OSI Approved :: Apache Software License
Classifier: Programming Language :: Python :: 3
Classifier: Programming Language :: Python :: 3.5
Classifier: Programming Language :: Python :: 3.6
Classifier: Programming Language :: Python :: 3.7
Classifier: Programming Language :: Python :: 3.8
Classifier: Programming Language :: Python :: 3.9
License-File: LICENSE.txt
